ptetools/__init__.py
ptetools/_qtt.py
ptetools/collections.py
ptetools/computation.py
ptetools/geometry.py
ptetools/optimization.py
ptetools/qi.py
ptetools/qiskit.py
ptetools/qutip.py
ptetools/tools.py
ptetools/version.py
ptetools-0.1.23.dist-info/licenses/LICENSE.md
ptetools-0.1.23.dist-info/METADATA
ptetools-0.1.23.dist-info/WHEEL
ptetools-0.1.23.dist-info/top_level.txt
ptetools-0.1.23.dist-info/RECORD
